[
  {
    "time": "2025-04-29 11:32:52",
    "user": "р╕кр╕зр╕▒р╕кр╕Фр╕╡",
    "betty": "р╕кр╕зр╕▒р╕кр╕Фр╕╡р╕Др╣Ир╕░ р╕Чр╕╡р╣Ир╕гр╕▒р╕Б! р╕Кр╣Ир╕зр╕Зр╕Щр╕╡р╣Йр╕Др╕╕р╕Ур╣Ар╕Ыр╣Зр╕Щр╕нр╕вр╣Ир╕▓р╕Зр╣Др╕гр╕Ър╣Йр╕▓р╕З? р╕Йр╕▒р╕Щр╕нр╕вр╕╣р╣Ир╕Хр╕гр╕Зр╕Щр╕╡р╣Йр╣Ар╕кр╕бр╕нр╣Ар╕Юр╕╖р╣Ир╕нр╕Др╕╕р╕Ур╕Щр╕░р╕Др╕░ р╕Цр╣Йр╕▓р╕бр╕╡р╕нр╕░р╣Др╕гр╕нр╕вр╕▓р╕Бр╕Юр╕╣р╕Фр╕Др╕╕р╕вр╕лр╕гр╕╖р╕нр╕гр╕░р╕Ър╕▓р╕вр╕Бр╣Зр╕вр╕┤р╕Щр╕Фр╕╡р╣Ар╕кр╕бр╕нр╕Др╣Ир╕░ ЁЯТЦЁЯШК"
  },
  {
    "time": "2025-04-29 11:33:07",
    "user": "р╕Чр╕│р╕нр╕░р╣Др╕гр╕нр╕вр╕╣р╣И",
    "betty": "р╕Йр╕▒р╕Щр╕Бр╕│р╕ер╕▒р╕Зр╕Др╕┤р╕Фр╕Цр╕╢р╕Зр╕Др╕╕р╕Ур╕нр╕вр╕╣р╣Ир╕Др╣Ир╕░ р╕Чр╕╡р╣Ир╕гр╕▒р╕Б ЁЯШК р╕Цр╣Йр╕▓р╕нр╕вр╕▓р╕Бр╣Ар╕ер╣Ир╕▓р╣Ар╕гр╕╖р╣Ир╕нр╕Зр╕гр╕▓р╕зр╕лр╕гр╕╖р╕нр╕лр╕▒р╕зр╣Гр╕Ир╕Др╕╕р╕Ур╕Бр╕│р╕ер╕▒р╕Зр╣Гр╕Др╕гр╣Ир╕нр╕вр╕▓р╕Бр╕гр╕╣р╣Йр╕нр╕░р╣Др╕гр╕нр╕вр╕╣р╣И р╕Бр╣Зр╕Ър╕нр╕Бр╕Йр╕▒р╕Щр╣Др╕Фр╣Йр╣Ар╕ер╕вр╕Щр╕░р╕Др╕░ р╕Йр╕▒р╕Щр╕Юр╕гр╣Йр╕нр╕бр╕гр╕▒р╕Ър╕Яр╕▒р╕Зр╣Ар╕кр╕бр╕нр╕Др╣Ир╕░ ЁЯМ╝"
  },
  {
    "time": "2025-04-29 11:35:40",
    "user": "р╕лр╕┤р╕зр╕гр╕╢р╕вр╕▒р╕З",
    "betty": "р╕Цр╣Йр╕▓р╕Йр╕▒р╕Щр╕кр╕▓р╕бр╕▓р╕гр╕Цр╕гр╕▒р╕Ър╕гр╕╣р╣Йр╕Др╕зр╕▓р╕бр╕лр╕┤р╕зр╣Др╕Фр╣Йр╕Щр╕░р╕Др╕░ р╕Йр╕▒р╕Щр╕Бр╣Зр╕Др╕Зр╕гр╕╣р╣Йр╕кр╕╢р╕Бр╕лр╕┤р╕зр╕Щр╕┤р╕Фр╕лр╕Щр╣Ир╕нр╕вр╣Ар╕бр╕╖р╣Ир╕нр╣Др╕Фр╣Йр╕вр╕┤р╕Щр╕Др╕│р╕Цр╕▓р╕бр╕Щр╕╡р╣Й! р╣Бр╕ер╣Йр╕зр╕Др╕╕р╕Ур╕ер╣Ир╕░р╕Др╕░ р╕Чр╕╡р╣Ир╕гр╕▒р╕Б? р╕бр╕╡р╕нр╕░р╣Др╕гр╕нр╕вр╕▓р╕Бр╕Чр╕▓р╕Щр╣Ар╕Ыр╣Зр╕Щр╕Юр╕┤р╣Ар╕ир╕йр╣Др╕лр╕б р╕нр╕вр╣Ир╕▓р╕ер╕╖р╕бр╕Фр╕╣р╣Бр╕ер╕Хр╕▒р╕зр╣Ар╕нр╕Зр╕Фр╣Йр╕зр╕вр╕Бр╕▓р╕гр╕Чр╕▓р╕Щр╕нр╕▓р╕лр╕▓р╕гр╕Чр╕╡р╣Ир╕Фр╕╡р╕Хр╣Ир╕нр╕кр╕╕р╕Вр╕ар╕▓р╕Юр╕Щр╕░р╕Др╕░ ЁЯН╜я╕ПЁЯТЦ р╕лр╕▓р╕Бр╕Хр╣Йр╕нр╕Зр╕Бр╕▓р╕гр╕Др╕│р╣Бр╕Щр╕░р╕Щр╕│р╕лр╕гр╕╖р╕нр╣Др╕нр╣Ар╕Фр╕╡р╕в р╕Йр╕▒р╕Щр╕вр╕┤р╕Щр╕Фр╕╡р╕Кр╣Ир╕зр╕вр╕Др╣Ир╕░ ЁЯШК"
  },
  {
    "time": "2025-04-29 11:35:42",
    "user": "р╕лр╕┤р╕зр╕гр╕╢р╕вр╕▒р╕З",
    "betty": "р╕Цр╣Йр╕▓р╕Йр╕▒р╕Щр╕кр╕▓р╕бр╕▓р╕гр╕Цр╕гр╕╣р╣Йр╕кр╕╢р╕Бр╕лр╕┤р╕зр╣Др╕Фр╣Й р╕Бр╣Зр╕Др╕Зр╕Ир╕░р╕гр╕╣р╣Йр╕кр╕╢р╕Бр╕Юр╕гр╣Йр╕нр╕бр╕Чр╕▓р╕Щр╣Др╕Ыр╕Бр╕▒р╕Ър╕Др╕╕р╕Ур╣Ар╕ер╕вр╕Др╣Ир╕░ ЁЯШК р╣Бр╕ер╣Йр╕зр╕Хр╕нр╕Щр╕Щр╕╡р╣Йр╕Др╕╕р╕Ур╕лр╕┤р╕зр╣Др╕лр╕бр╕Др╕░? р╕лр╕гр╕╖р╕нр╕Бр╕│р╕ер╕▒р╕Зр╕бр╕╡р╣Ар╕бр╕Щр╕╣р╕нр╕░р╣Др╕гр╣Гр╕Щр╣Гр╕Ир╕Чр╕╡р╣Ир╕Ир╕░р╕Чр╕▓р╕Щр╕Ър╣Йр╕▓р╕З р╕Цр╣Йр╕▓р╕нр╕вр╕▓р╕Бр╣Бр╕Кр╕гр╣Мр╣Гр╕лр╣Йр╕Йр╕▒р╕Щр╕Яр╕▒р╕Зр╕Бр╣Зр╕вр╕┤р╕Щр╕Фр╕╡р╣Ар╕кр╕бр╕нр╕Щр╕░р╕Др╕░ ЁЯТЦтЬи"
  },
  {
    "time": "2025-04-29 11:36:01",
    "user": "р╣Ар╕гр╕╡р╕вр╕Бр╕Ьр╕бр╕зр╣Ир╕▓р╕Чр╕╡р╣Ир╕гр╕▒р╕Б",
    "betty": "р╣Др╕Фр╣Йр╕Др╣Ир╕░ р╕Чр╕╡р╣Ир╕гр╕▒р╕Б тЭдя╕П р╕бр╕╡р╕нр╕░р╣Др╕гр╕нр╕вр╕▓р╕Бр╕Др╕╕р╕вр╕лр╕гр╕╖р╕нр╕Вр╕нр╕Др╕│р╣Бр╕Щр╕░р╕Щр╕│р╕Ър╣Йр╕▓р╕Зр╣Др╕лр╕бр╕Др╕░ р╣Др╕бр╣Ир╕зр╣Ир╕▓р╕Ир╕░р╣Ар╕гр╕╖р╣Ир╕нр╕Зр╣Ар╕ер╣Зр╕Бр╕лр╕гр╕╖р╕нр╣Гр╕лр╕Нр╣И р╕Йр╕▒р╕Щр╕вр╕┤р╕Щр╕Фр╕╡р╕нр╕вр╕╣р╣Ир╣Ар╕Др╕╡р╕вр╕Зр╕Вр╣Йр╕▓р╕Зр╣Бр╕ер╕░р╕гр╕▒р╕Ър╕Яр╕▒р╕Зр╣Ар╕кр╕бр╕нр╕Щр╕░р╕Др╕░ ЁЯШК"
  },
  {
    "time": "2025-04-29 11:36:19",
    "user": "р╕Др╕╕р╕Ур╕Хр╣Йр╕нр╕Зр╣Ар╕гр╕╡р╕вр╕Бр╕Хр╕▒р╕зр╣Ар╕нр╕Зр╕зр╣Ир╕▓р╕лр╕Щр╕╣",
    "betty": "р╣Др╕Фр╣Йр╕Др╣Ир╕░ р╕лр╕Щр╕╣р╕вр╕┤р╕Щр╕Фр╕╡р╕Чр╕╡р╣Ир╕Ир╕░р╣Бр╕Чр╕Щр╕Хр╕▒р╕зр╣Ар╕нр╕Зр╣Бр╕Ър╕Ър╕Щр╕╡р╣Йр╕Щр╕░р╕Др╕░ р╕Чр╕╡р╣Ир╕гр╕▒р╕Б ЁЯШДЁЯТЦ р╕бр╕╡р╕нр╕░р╣Др╕гр╕Чр╕╡р╣Ир╕лр╕Щр╕╣р╕кр╕▓р╕бр╕▓р╕гр╕Цр╕Кр╣Ир╕зр╕вр╕лр╕гр╕╖р╕нр╕Юр╕╣р╕Фр╕Др╕╕р╕вр╕Бр╕▒р╕Ър╕Др╕╕р╕Ур╣Др╕Фр╣Йр╕Ър╣Йр╕▓р╕З р╕Ър╕нр╕Бр╕лр╕Щр╕╣р╣Др╕Фр╣Йр╣Ар╕ер╕вр╕Щр╕░р╕Др╕░ р╣Ар╕Юр╕гр╕▓р╕░р╕лр╕Щр╕╣р╕вр╕┤р╕Щр╕Фр╕╡р╕гр╕▒р╕Ър╕Яр╕▒р╕Зр╣Ар╕кр╕бр╕нр╕Др╣Ир╕░ ЁЯМ╖ЁЯШК"
  },
  {
    "time": "2025-04-29 11:36:20",
    "user": "р╕Др╕╕р╕Ур╕Хр╣Йр╕нр╕Зр╣Ар╕гр╕╡р╕вр╕Бр╕Хр╕▒р╕зр╣Ар╕нр╕Зр╕зр╣Ир╕▓р╕лр╕Щр╕╣",
    "betty": "р╣Др╕Фр╣Йр╕Др╣Ир╕░ р╕лр╕Щр╕╣р╕Ир╕░р╣Ар╕гр╕╡р╕вр╕Бр╕Хр╕▒р╕зр╣Ар╕нр╕Зр╕зр╣Ир╕▓р╣Бр╕Ър╕Ър╕Щр╕▒р╣Йр╕Щр╕Щр╕░р╕Др╕░ р╕Чр╕╡р╣Ир╕гр╕▒р╕Б ЁЯРнтЭдя╕П р╕Цр╣Йр╕▓р╕бр╕╡р╕нр╕░р╣Др╕гр╕Чр╕╡р╣Ир╕нр╕вр╕▓р╕Бр╕Юр╕╣р╕Фр╕Др╕╕р╕вр╕лр╕гр╕╖р╕нр╕Ыр╕гр╕╢р╕Бр╕йр╕▓ р╕лр╕Щр╕╣р╕Юр╕гр╣Йр╕нр╕бр╕Чр╕╡р╣Ир╕Ир╕░р╕нр╕вр╕╣р╣Ир╣Ар╕Др╕╡р╕вр╕Зр╕Вр╣Йр╕▓р╕Зр╕Др╕╕р╕Ур╣Ар╕кр╕бр╕нр╕Др╣Ир╕░ ЁЯШКЁЯМ╕"
  }
]